{
  "project_info": {
    "project_number": "690713565687",
    "project_id": "untitled1-e9371",
    "storage_bucket": "untitled1-e9371.appspot.com"
  },
  "client": [
    {
      "client_info": {
        "mobilesdk_app_id": "1:690713565687:android:c1e888bce68c91053bb6f2",
        "android_client_info": {
          "package_name": "com.example.untitled1"
        }
      },
      "oauth_client": [
        {
          "client_id": "690713565687-4m0u2garjj0827gaja9v16e04rje61tk.apps.googleusercontent.com",
          "client_type": 3
        }
      ],
      "api_key": [
        {
          "current_key": "AIzaSyDWBIhH8S6n2EqpZKtYNarC9Tbxv8RkzgY"
        }
      ],
      "services": {
        "appinvite_service": {
          "other_platform_oauth_client": [
            {
              "client_id": "690713565687-4m0u2garjj0827gaja9v16e04rje61tk.apps.googleusercontent.com",
              "client_type": 3
            }
          ]
        }
      }
    }
  ],
  "configuration_version": "1"
}